codable/__init__.py
codable/json.py
codable/serialization.py
tests/__init__.py
tests/test_coding_containers.py
codable-0.1.1.dist-info/METADATA
codable-0.1.1.dist-info/WHEEL
codable-0.1.1.dist-info/top_level.txt
codable-0.1.1.dist-info/RECORD
