Metadata-Version: 2.1
Name: codable
Version: 0.1.1
Summary: A Python module for encoding and decoding objects using customizable serialization.
Home-page: https://github.com/igutekunst/python-codable
Author: Isaac Harrison Gutekunst
Author-email: isaac@dancingvoid.com
Classifier: Programming Language :: Python :: 3
Classifier: License :: OSI Approved :: MIT License
Classifier: Operating System :: OS Independent
Requires-Python: >=3.6
Provides-Extra: testing
Requires-Dist: pytest ; extra == 'testing'
